[
  {
    "ayat": 1,
    "arabic": "وَالصّٰۤفّٰتِ صَفًّاۙ",
    "transliteration_en": "Wassaaaffaati saffaa",
    "transliteration_id": "Waṣ-ṣāffāti ṣaffā(n).",
    "translation_en": "By those [angels] lined up in rows",
    "translation_id": "Demi (rombongan malaikat) yang berbaris bersaf-saf, (untuk beribadah kepada Allah),"
  },
  {
    "ayat": 2,
    "arabic": "فَالزّٰجِرٰتِ زَجْرًاۙ",
    "transliteration_en": "Fazzaajiraati zajraa",
    "transliteration_id": "Faz-zājirāti zajrā(n).",
    "translation_en": "And those who drive [the clouds]",
    "translation_id": "demi (rombongan malaikat) yang mencegah (segala sesuatu) dengan sungguh-sungguh,"
  },
  {
    "ayat": 3,
    "arabic": "فَالتّٰلِيٰتِ ذِكْرًاۙ",
    "transliteration_en": "Fattaaliyaati Zikra",
    "transliteration_id": "Fat-tāliyāti żikrā(n).",
    "translation_en": "And those who recite the message,",
    "translation_id": "demi (rombongan malaikat) yang membacakan peringatan,"
  },
  {
    "ayat": 4,
    "arabic": "اِنَّ اِلٰهَكُمْ لَوَاحِدٌۗ",
    "transliteration_en": "Inna Illaahakum la Waahid",
    "transliteration_id": "Inna ilāhakum lawāḥid(un).",
    "translation_en": "Indeed, your God is One,",
    "translation_id": "sungguh, Tuhanmu benar-benar Esa."
  },
  {
    "ayat": 5,
    "arabic": "رَبُّ السَّمٰوٰتِ وَالْاَرْضِ وَمَا بَيْنَهُمَا وَرَبُّ الْمَشَارِقِۗ",
    "transliteration_en": "Rabbus samaawaati wal ardi wa maa bainahumaa wa Rabbul mashaariq",
    "transliteration_id": "Rabbus-samāwāti wal-arḍi wa mā bainahumā wa rabbul-masyāriq(i).",
    "translation_en": "Lord of the heavens and the earth and that between them and Lord of the sunrises.",
    "translation_id": "Tuhan langit dan bumi dan apa yang berada di antara keduanya dan Tuhan tempat-tempat terbitnya matahari."
  },
  {
    "ayat": 6,
    "arabic": "اِنَّا زَيَّنَّا السَّمَاۤءَ الدُّنْيَا بِزِيْنَةِ ِۨالْكَوَاكِبِۙ",
    "transliteration_en": "Innaa zaiyannas samaaa 'ad dunyaa bizeenatinil kawaakib",
    "transliteration_id": "Innā zayyannas-samā'ad-dun-yā bizīnatinil-kawākib(i).",
    "translation_en": "Indeed, We have adorned the nearest heaven with an adornment of stars",
    "translation_id": "Sesungguhnya Kami telah menghiasi langit dunia (yang terdekat) dengan hiasan (berupa) bintang-bintang."
  },
  {
    "ayat": 7,
    "arabic": "وَحِفْظًا مِّنْ كُلِّ شَيْطٰنٍ مَّارِدٍۚ",
    "transliteration_en": "Wa hifzam min kulli Shaitaanim maarid",
    "transliteration_id": "Wa ḥifẓam min kulli syaiṭānim mārid(in).",
    "translation_en": "And as protection against every rebellious devil",
    "translation_id": "(Kami telah menjaganya dengan) penjagaan yang sempurna dari setiap setan yang durhaka."
  },
  {
    "ayat": 8,
    "arabic": "لَا يَسَّمَّعُوْنَ اِلَى الْمَلَاِ الْاَعْلٰى وَيُقْذَفُوْنَ مِنْ كُلِّ جَانِبٍۖ",
    "transliteration_en": "Laa yassamma 'oona ilal mala il a'alaa wa yuqzafoona min kulli jaanib",
    "transliteration_id": "Lā yassammā‘ūna ilal-mala'il-a‘lā wa yuqżafūna min kulli jānib(in).",
    "translation_en": "[So] they may not listen to the exalted assembly [of angels] and are pelted from every side,",
    "translation_id": "Mereka (setan-setan) tidak dapat mendengar (percakapan) para malaikat dan mereka dilempari dari segala penjuru"
  },
  {
    "ayat": 9,
    "arabic": "دُحُوْرًا وَّلَهُمْ عَذَابٌ وَّاصِبٌ",
    "transliteration_en": "Duhooranw wa lahum 'azaabunw waasib",
    "transliteration_id": "Duḥūraw wa lahum ‘ażābuw wāṣib(un).",
    "translation_en": "Repelled; and for them is a constant punishment,",
    "translation_id": "untuk mengusir mereka. Bagi mereka azab yang kekal (di akhirat),"
  },
  {
    "ayat": 10,
    "arabic": "اِلَّا مَنْ خَطِفَ الْخَطْفَةَ فَاَتْبَعَهٗ شِهَابٌ ثَاقِبٌ",
    "transliteration_en": "Illaa man khatifal khatfata fa atba'ahoo shihaabun saaqib",
    "transliteration_id": "Illā man khaṭifal-khaṭfata fa'atba‘ahū syihābun ṡāqib(un).",
    "translation_en": "Except one who snatches [some words] by theft, but they are pursued by a burning flame, piercing [in brightness].",
    "translation_id": "kecuali (setan) yang menyambar pembicaraan dengan sekali sambar; maka ia dikejar oleh bintang yang menyala."
  },
  {
    "ayat": 11,
    "arabic": "فَاسْتَفْتِهِمْ اَهُمْ اَشَدُّ خَلْقًا اَمْ مَّنْ خَلَقْنَا ۗاِنَّا خَلَقْنٰهُمْ مِّنْ طِيْنٍ لَّازِبٍ",
    "transliteration_en": "Fastaftihim ahum ashaddu khalqan am man khalaqnaa; innaa khalaqnaahum min teenil laazib",
    "transliteration_id": "Fastaftihim ahum asyaddu khalqan am man khalaqnā, innā khalaqnāhum min ṭīnil lāzib(in).",
    "translation_en": "Then inquire of them, [O Muhammad], \"Are they a stronger [or more difficult] creation or those [others] We have created?\" Indeed, We created men from sticky clay.",
    "translation_id": "Maka, tanyakanlah kepada mereka (musyrik Makkah), “Apakah mereka (manusia) lebih sulit penciptaannya ataukah selainnya (langit, bumi, dan lainnya) yang telah Kami ciptakan?” Sesungguhnya Kami telah menciptakan (bapak) mereka (Adam) dari tanah liat."
  },
  {
    "ayat": 12,
    "arabic": "بَلْ عَجِبْتَ وَيَسْخَرُوْنَ ۖ",
    "transliteration_en": "Bal'ajibta wa yaskharoon",
    "transliteration_id": "Bal ‘ajibta wa yaskharūn(a).",
    "translation_en": "But you wonder, while they mock,",
    "translation_id": "Bahkan, engkau (Nabi Muhammad) menjadi heran (terhadap keingkaran mereka) dan mereka selalu menghinamu."
  },
  {
    "ayat": 13,
    "arabic": "وَاِذَا ذُكِّرُوْا لَا يَذْكُرُوْنَ ۖ",
    "transliteration_en": "Wa izaa zukkiroo laa yazkuroon",
    "transliteration_id": "Wa iżā żukkirū lā yażkurūn(a).",
    "translation_en": "And when they are reminded, they remember not.",
    "translation_id": "Apabila diberi peringatan, mereka tidak mengingat (mengindahkannya)."
  },
  {
    "ayat": 14,
    "arabic": "وَاِذَا رَاَوْا اٰيَةً يَّسْتَسْخِرُوْنَۖ",
    "transliteration_en": "Wa izaa ra aw Aayatinw yastaskhiroon",
    "transliteration_id": "Wa iżā ra'au āyatay yastaskhirūn(a).",
    "translation_en": "And when they see a sign, they ridicule",
    "translation_id": "Apabila melihat suatu tanda (kebesaran Allah atau kebenaran Nabi Muhammad), mereka sangat menghina."
  },
  {
    "ayat": 15,
    "arabic": "وَقَالُوْٓا اِنْ هٰذَآ اِلَّا سِحْرٌ مُّبِيْنٌ ۚ",
    "transliteration_en": "Wa qaalooo in haazaa illaa sihrum mubeen",
    "transliteration_id": "Wa qālū in hāżā illā siḥrum mubīn(un).",
    "translation_en": "And say, \"This is not but obvious magic.",
    "translation_id": "Mereka berkata, “Ini tidak lain hanyalah sihir yang nyata."
  },
  {
    "ayat": 16,
    "arabic": "ءَاِذَا مِتْنَا وَكُنَّا تُرَابًا وَّعِظَامًا ءَاِنَّا لَمَبْعُوْثُوْنَۙ",
    "transliteration_en": "'A-izaa mitnaa wa kunnaa turaabanw wa 'izaaman 'ainnaa lamab'oosoon",
    "transliteration_id": "A'iżā mitnā wa kunnā turābaw wa ‘iẓāman a'innā lamab‘ūṡūn(a).",
    "translation_en": "When we have died and become dust and bones, are we indeed to be resurrected?",
    "translation_id": "Apabila kami telah mati, (lalu) menjadi tanah dan tulang-belulang, apakah kami benar-benar akan dibangkitkan?"
  },
  {
    "ayat": 17,
    "arabic": "اَوَاٰبَاۤؤُنَا الْاَوَّلُوْنَۗ",
    "transliteration_en": "Awa aabaa'unal awwaloon",
    "transliteration_id": "Awa ābā'unal-awwalūn(a).",
    "translation_en": "And our forefathers [as well]?\"",
    "translation_id": "Apakah nenek moyang kami yang terdahulu (akan dibangkitkan pula)?”"
  },
  {
    "ayat": 18,
    "arabic": "قُلْ نَعَمْ وَاَنْتُمْ دٰخِرُوْنَۚ",
    "transliteration_en": "Qul na'am wa antum daakhiroon",
    "transliteration_id": "Qul na‘am wa antum dākhirūn(a).",
    "translation_en": "Say, \"Yes, and you will be [rendered] contemptible.\"",
    "translation_id": "Katakanlah (Nabi Muhammad), “Ya (kamu akan dibangkitkan) dan kamu akan terhina.”"
  },
  {
    "ayat": 19,
    "arabic": "فَاِنَّمَا هِيَ زَجْرَةٌ وَّاحِدَةٌ فَاِذَا هُمْ يَنْظُرُوْنَ",
    "transliteration_en": "Fa innamaa hiya zajra tunw waahidatun fa izaa hum yanzuroon",
    "transliteration_id": "Fa'innamā hiya zajratuw wāḥidatun fa'iżā hum yanẓurūn(a).",
    "translation_en": "It will be only one shout, and at once they will be observing.",
    "translation_id": "Sesungguhnya kebangkitan itu hanya dengan satu teriakan (tiupan sangkakala kedua). Maka, seketika itu mereka (bangun dari kematiannya) melihat (apa yang terjadi)."
  },
  {
    "ayat": 20,
    "arabic": "وَقَالُوْا يٰوَيْلَنَا هٰذَا يَوْمُ الدِّيْنِ",
    "transliteration_en": "Qa qaaloo yaa wailanaa haazaa Yawmud-Deen",
    "transliteration_id": "Wa qālū yā wailanā hāżā yaumud-dīn(i).",
    "translation_en": "They will say, \"O woe to us! This is the Day of Recompense.\"",
    "translation_id": "Mereka berkata, “Alangkah celaka kami! (Kiranya) inilah hari Pembalasan itu.”"
  },
  {
    "ayat": 21,
    "arabic": "هٰذَا يَوْمُ الْفَصْلِ الَّذِيْ كُنْتُمْ بِهٖ تُكَذِّبُوْنَ ࣖ",
    "transliteration_en": "Haazaa Yawmul Faslil lazee kuntum bihee tukaziboon",
    "transliteration_id": "Hāżā yaumul-faṣlil-lażī kuntum bihī tukażżibūn(a).",
    "translation_en": "[They will be told], \"This is the Day of Judgement which you used to deny.\"",
    "translation_id": "Inilah hari keputusan yang dahulu (selalu) kamu dustakan."
  },
  {
    "ayat": 22,
    "arabic": "اُحْشُرُوا الَّذِيْنَ ظَلَمُوْا وَاَزْوَاجَهُمْ وَمَا كَانُوْا يَعْبُدُوْنَ ۙ",
    "transliteration_en": "Uhshurul lazeena zalamoo wa azwaajahum wa maa kaanoo ya'budoon",
    "transliteration_id": "Uḥsyurul-lażīna ẓalamū wa azwājahum wa mā kānū ya‘budūn(a).",
    "translation_en": "[The angels will be ordered], \"Gather those who committed wrong, their kinds, and what they used to worship",
    "translation_id": "(Lalu, diperintahkan kepada para malaikat,) “Kumpulkanlah orang-orang yang zalim beserta teman sejawat mereka dan apa yang dahulu mereka sembah"
  },
  {
    "ayat": 23,
    "arabic": "مِنْ دُوْنِ اللّٰهِ فَاهْدُوْهُمْ اِلٰى صِرَاطِ الْجَحِيْمِ",
    "transliteration_en": "Min doonil laahi fahdoohum ilaa siraatil Jaheem",
    "transliteration_id": "Min dūnillāhi fahdūhum ilā ṣirāṭil-jaḥīm(i).",
    "translation_en": "Other than Allah, and guide them to the path of Hellfire",
    "translation_id": "selain Allah. Lalu, tunjukkanlah kepada mereka jalan ke (neraka) Jahim."
  },
  {
    "ayat": 24,
    "arabic": "وَقِفُوْهُمْ اِنَّهُمْ مَّسْـُٔوْلُوْنَ ۙ",
    "transliteration_en": "Wa qifoohum innahum mas'ooloon",
    "transliteration_id": "Waqifūhum innahum mas'ūlūn(a).",
    "translation_en": "And stop them; indeed, they are to be questioned.\"",
    "translation_id": "Tahanlah mereka (di tempat perhentian). Sesungguhnya mereka akan ditanya (tentang keyakinan dan perilaku mereka).”"
  },
  {
    "ayat": 25,
    "arabic": "مَا لَكُمْ لَا تَنَاصَرُوْنَ",
    "transliteration_en": "Maa lakum laa tanaasaroon",
    "transliteration_id": "Mā lakum lā tanāṣarūn(a).",
    "translation_en": "[They will be asked], \"What is [wrong] with you? Why do you not help each other?\"",
    "translation_id": "(Mereka lalu dikecam,) “Mengapa kamu tidak tolong-menolong (sebagaimana kamu di dunia)?”"
  },
  {
    "ayat": 26,
    "arabic": "بَلْ هُمُ الْيَوْمَ مُسْتَسْلِمُوْنَ",
    "transliteration_en": "Bal humul Yawma mustaslimoon",
    "transliteration_id": "Bal humul-yauma mustaslimūn(a).",
    "translation_en": "But they, that Day, are in surrender.",
    "translation_id": "Bahkan, mereka pada hari itu menyerah (kepada putusan Allah)."
  },
  {
    "ayat": 27,
    "arabic": "وَاَقْبَلَ بَعْضُهُمْ عَلٰى بَعْضٍ يَّتَسَاۤءَلُوْنَ",
    "transliteration_en": "Wa aqbala ba'duhum 'alaa ba'diny yatasaaa'aloon",
    "transliteration_id": "Wa aqbala ba‘ḍuhum ‘alā ba‘ḍiy yatasā'alūn(a).",
    "translation_en": "And they will approach one another blaming each other.",
    "translation_id": "Sebagian mereka menghadap kepada sebagian yang lain saling bertanya (berbantah-bantahan)."
  },
  {
    "ayat": 28,
    "arabic": "قَالُوْٓا اِنَّكُمْ كُنْتُمْ تَأْتُوْنَنَا عَنِ الْيَمِيْنِ",
    "transliteration_en": "Qaalooo innakum kuntum taatoonanaa 'anil yameen",
    "transliteration_id": "Qālū innakum kuntum ta'tūnanā ‘anil-yamīn(i).",
    "translation_en": "They will say, \"Indeed, you used to come at us from the right.\"",
    "translation_id": "(Pengikut) mereka berkata (kepada pemimpinnya), “Sesungguhnya kamulah yang dahulu selalu mendatangi kami dari arah kanan (untuk menghalangi kami dari kebajikan).”"
  },
  {
    "ayat": 29,
    "arabic": "قَالُوْا بَلْ لَّمْ تَكُوْنُوْا مُؤْمِنِيْنَۚ",
    "transliteration_en": "Qaaloo bal lam takoonoo mu'mineen",
    "transliteration_id": "Qālū bal lam takūnū mu'minīn(a).",
    "translation_en": "The oppressors will say, \"Rather, you [yourselves] were not believers,",
    "translation_id": "(Pemimpin) mereka menjawab, “(Tidak,) bahkan kamulah yang tidak (mau) menjadi orang mukmin."
  },
  {
    "ayat": 30,
    "arabic": "وَمَا كَانَ لَنَا عَلَيْكُمْ مِّنْ سُلْطٰنٍۚ بَلْ كُنْتُمْ قَوْمًا طٰغِيْنَ",
    "transliteration_en": "Wa maa kaana lanaa 'alaikum min sultaanim bal kuntum qawman taagheen",
    "transliteration_id": "Wa mā kāna lanā ‘alaikum min sulṭān(in), bal kuntum qauman ṭāgīn(a).",
    "translation_en": "And we had over you no authority, but you were a transgressing people.",
    "translation_id": "(Sebenarnya,) kami sedikit pun tidak berkuasa terhadapmu (untuk menghalang-halangimu), bahkan kamulah kaum yang melampaui batas."
  },
  {
    "ayat": 31,
    "arabic": "فَحَقَّ عَلَيْنَا قَوْلُ رَبِّنَآ  ۖاِنَّا لَذَاۤىِٕقُوْنَ",
    "transliteration_en": "Fahaqqa 'alainaa qawlu Rabbinaaa innaa lazaaa'iqoon",
    "transliteration_id": "Fa ḥaqqa ‘alainā qaulu rabbinā, innā lażā'iqūn(a).",
    "translation_en": "So the word of our Lord has come into effect upon us; indeed, we will taste [punishment].",
    "translation_id": "Maka, putusan (azab) Tuhan (akan) benar-benar menimpa kita. Pasti kita akan merasakan (azab itu)."
  },
  {
    "ayat": 32,
    "arabic": "فَاَغْوَيْنٰكُمْ اِنَّا كُنَّا غٰوِيْنَ",
    "transliteration_en": "Fa aghwainaakum innaa kunnaa ghaaween",
    "transliteration_id": "Fa agwainākum innā kunnā gāwīn(a).",
    "translation_en": "And we led you to deviation; indeed, we were deviators.\"",
    "translation_id": "Kami (mengakui) telah menyesatkan kamu. Sesungguhnya kami sendiri orang-orang yang sesat.”"
  },
  {
    "ayat": 33,
    "arabic": "فَاِنَّهُمْ يَوْمَىِٕذٍ فِى الْعَذَابِ مُشْتَرِكُوْنَ",
    "transliteration_en": "Fa innahum Yawma'izin fil'azaabi mushtarikoon",
    "transliteration_id": "Fa innahum yauma'iżin fil-‘ażābi musytarikūn(a).",
    "translation_en": "So indeed they, that Day, will be sharing in the punishment.",
    "translation_id": "Sesungguhnya mereka pada hari itu bersama-sama merasakan azab."
  },
  {
    "ayat": 34,
    "arabic": "اِنَّا كَذٰلِكَ نَفْعَلُ بِالْمُجْرِمِيْنَ",
    "transliteration_en": "Innaa kazaalika naf'alu bil mujrimeen",
    "transliteration_id": "Innā każālika naf‘alu bil-mujrimīn(a).",
    "translation_en": "Indeed, that is how We deal with the criminals.",
    "translation_id": "Sesungguhnya demikianlah Kami memperlakukan orang-orang yang berbuat dosa."
  },
  {
    "ayat": 35,
    "arabic": "اِنَّهُمْ كَانُوْٓا اِذَا قِيْلَ لَهُمْ لَآ اِلٰهَ اِلَّا اللّٰهُ يَسْتَكْبِرُوْنَ ۙ",
    "transliteration_en": "Innahum kaanooo izaa qeela lahum laaa ilaaha illal laahu yastakbiroon",
    "transliteration_id": "Innahum kānū iżā qīla lahum lā ilāha illallāhu yastakbirūn(a).",
    "translation_en": "Indeed they, when it was said to them, \"There is no deity but Allah,\" were arrogant",
    "translation_id": "Sesungguhnya dahulu apabila dikatakan kepada mereka, “Lā ilāha illallāh” (Tidak ada tuhan selain Allah), mereka menyombongkan diri."
  },
  {
    "ayat": 36,
    "arabic": "وَيَقُوْلُوْنَ اَىِٕنَّا لَتَارِكُوْٓا اٰلِهَتِنَا لِشَاعِرٍ مَّجْنُوْنٍ ۗ",
    "transliteration_en": "Wa yaqooloona a'innaa lataarikooo aalihatinaa lishaa'irim majnoon",
    "transliteration_id": "Wa yaqūlūna a'innā latārikū ālihatinā lisyā‘irim majnūn(in).",
    "translation_en": "And were saying, \"Are we to leave our gods for a mad poet?\"",
    "translation_id": "Mereka berkata, “Apakah kami harus meninggalkan sesembahan kami karena seorang penyair gila?”"
  },
  {
    "ayat": 37,
    "arabic": "بَلْ جَاۤءَ بِالْحَقِّ وَصَدَّقَ الْمُرْسَلِيْنَ",
    "transliteration_en": "bal jaaa'a bilhaqqi wa saddaqal mursaleen",
    "transliteration_id": "Bal jā'a bil-ḥaqqi wa ṣaddaqal-mursalīn(a).",
    "translation_en": "Rather, the Prophet has come with the truth and confirmed the [previous] messengers.",
    "translation_id": "Padahal dia (Nabi Muhammad) datang dengan membawa kebenaran dan membenarkan para rasul (sebelumnya)."
  },
  {
    "ayat": 38,
    "arabic": "اِنَّكُمْ لَذَاۤىِٕقُوا الْعَذَابِ الْاَلِيْمِ ۚ",
    "transliteration_en": "Innakum lazaaa'iqul 'azaabil aleem",
    "transliteration_id": "Innakum lażā'iqul-‘ażābil-alīm(i).",
    "translation_en": "Indeed, you [disbelievers] will be tasters of the painful punishment,",
    "translation_id": "Sesungguhnya kamu pasti akan merasakan azab yang pedih."
  },
  {
    "ayat": 39,
    "arabic": "وَمَا تُجْزَوْنَ اِلَّا مَا كُنْتُمْ تَعْمَلُوْنَۙ",
    "transliteration_en": "Wa maa tujzawna illaa maa kuntum ta'maloon",
    "transliteration_id": "Wa mā tujzauna illā mā kuntum ta‘malūn(a).",
    "translation_en": "And you will not be recompensed except for what you used to do -",
    "translation_id": "Kamu tidak diberi balasan, kecuali terhadap apa yang telah kamu kerjakan."
  },
  {
    "ayat": 40,
    "arabic": "اِلَّا عِبَادَ اللّٰهِ الْمُخْلَصِيْنَ",
    "transliteration_en": "Illaa 'ibaadal laahil mukhlaseen",
    "transliteration_id": "Illā ‘ibādallāhil-mukhlaṣīn(a).",
    "translation_en": "But not the chosen servants of Allah.",
    "translation_id": "Akan tetapi, hamba-hamba Allah yang terpilih (karena keikhlasannya),"
  },
  {
    "ayat": 41,
    "arabic": "اُولٰۤىِٕكَ لَهُمْ رِزْقٌ مَّعْلُوْمٌۙ",
    "transliteration_en": "Ulaaa'ika lahum rizqum ma'loom",
    "transliteration_id": "Ulā'ika lahum rizqum ma‘lūm(un).",
    "translation_en": "Those will have a provision determined -",
    "translation_id": "mereka itu memperoleh rezeki yang sudah ditentukan,"
  },
  {
    "ayat": 42,
    "arabic": "فَوَاكِهُ ۚوَهُمْ مُّكْرَمُوْنَۙ",
    "transliteration_en": "Fa waakihu wa hum mukramoon",
    "transliteration_id": "Fawākihu wa hum mukramūn(a).",
    "translation_en": "Fruits; and they will be honored",
    "translation_id": "(yaitu) buah-buahan. Mereka adalah orang-orang yang dimuliakan"
  },
  {
    "ayat": 43,
    "arabic": "فِيْ جَنّٰتِ النَّعِيْمِۙ",
    "transliteration_en": "Fee jannaatin Na'eem",
    "transliteration_id": "Fī jannātin na‘īm(i).",
    "translation_en": "In gardens of pleasure",
    "translation_id": "di dalam surga-surga yang penuh kenikmatan."
  },
  {
    "ayat": 44,
    "arabic": "عَلٰى سُرُرٍ مُّتَقٰبِلِيْنَ",
    "transliteration_en": "'Alaa sururim mutaqaa bileen",
    "transliteration_id": "‘Alā sururim mutaqābilīn(a).",
    "translation_en": "On thrones facing one another.",
    "translation_id": "(Mereka duduk) berhadap-hadapan di atas dipan-dipan."
  },
  {
    "ayat": 45,
    "arabic": "يُطَافُ عَلَيْهِمْ بِكَأْسٍ مِّنْ مَّعِيْنٍۢ ۙ",
    "transliteration_en": "Yutaafu 'alaihim bikaasim mim ma'een",
    "transliteration_id": "Yuṭāfu ‘alaihim bika'sim mim ma‘īn(in).",
    "translation_en": "There will be circulated among them a cup [of wine] from a flowing spring,",
    "translation_id": "Kepada mereka diedarkan gelas (yang berisi minuman) dari mata air (surga)."
  },
  {
    "ayat": 46,
    "arabic": "بَيْضَاۤءَ لَذَّةٍ لِّلشّٰرِبِيْنَۚ",
    "transliteration_en": "Baidaaa'a laz zatil lish shaaribeen",
    "transliteration_id": "Baiḍā'a lażżatil lisy-syāribīn(a).",
    "translation_en": "White and delicious to the drinkers;",
    "translation_id": "(Warnanya) putih bersih dan lezat rasanya bagi orang-orang yang meminum(-nya)."
  },
  {
    "ayat": 47,
    "arabic": "لَا فِيْهَا غَوْلٌ وَّلَا هُمْ عَنْهَا يُنْزَفُوْنَ",
    "transliteration_en": "Laa feehaa ghawlunw wa laa hum 'anhaa yunzafoon",
    "transliteration_id": "Lā fīhā gauluw wa lā hum ‘anhā yunzafūn(a).",
    "translation_en": "No bad effect is there in it, nor from it will they be intoxicated.",
    "translation_id": "Tidak ada di dalamnya (unsur) yang membahayakan dan mereka tidak mabuk karenanya."
  },
  {
    "ayat": 48,
    "arabic": "وَعِنْدَهُمْ قٰصِرٰتُ الطَّرْفِ عِيْنٌ ۙ",
    "transliteration_en": "Wa 'indahum qaasiraatut tarfi 'een",
    "transliteration_id": "Wa ‘indahum qāṣirātuṭ-ṭarfi ‘īn(un).",
    "translation_en": "And with them will be women limiting [their] glances, with large, [beautiful] eyes,",
    "translation_id": "Di sisi mereka ada (bidadari-bidadari) yang bermata indah dan membatasi pandangannya (dari selain pasangan mereka)."
  },
  {
    "ayat": 49,
    "arabic": "كَاَنَّهُنَّ بَيْضٌ مَّكْنُوْنٌ",
    "transliteration_en": "Ka annahunna baidum maknoon",
    "transliteration_id": "Ka'annahum baiḍum maknūn(un).",
    "translation_en": "As if they were [delicate] eggs, well-protected.",
    "translation_id": "(Warna kulit) mereka seperti (warna) telur yang tersimpan dengan baik."
  },
  {
    "ayat": 50,
    "arabic": "فَاَقْبَلَ بَعْضُهُمْ عَلٰى بَعْضٍ يَّتَسَاۤءَلُوْنَ",
    "transliteration_en": "Fa aqbala ba'duhum 'alaa badiny yatasaaa 'aloon",
    "transliteration_id": "Fa'aqbala ba‘ḍuhum ‘alā ba‘ḍiy yatasā'alūn(a).",
    "translation_en": "And they will approach one another, inquiring of each other.",
    "translation_id": "Mereka berhadap-hadapan satu sama lain sambil bercakap-cakap."
  }
]